xqtor/__init__.py
xqtor-0.1.0.dist-info/METADATA
xqtor-0.1.0.dist-info/WHEEL
xqtor-0.1.0.dist-info/RECORD
