Metadata-Version: 2.1
Name: xqtor
Version: 0.1.0
Summary: Xqtor - a more flexible ThreadPoolExecutor
Author: Jackie Tung
Author-email: jackie.tung@gmail.com
Requires-Python: >=3.9
Classifier: Programming Language :: Python :: 3
Classifier: Programming Language :: Python :: 3.9
Classifier: Programming Language :: Python :: 3.10
Classifier: Programming Language :: Python :: 3.11
Classifier: Programming Language :: Python :: 3.12
